AI_Cdvst/__init__.py
AI_Cdvst-0.4.dist-info/METADATA
AI_Cdvst-0.4.dist-info/WHEEL
AI_Cdvst-0.4.dist-info/top_level.txt
AI_Cdvst-0.4.dist-info/RECORD
