Metadata-Version: 2.1
Name: AI-Cdvst
Version: 0.4
Summary: Eine Python-Bibliothek zur einfachen nutzung einer AI und API callsfürai.
Home-page: https://now4free.de/python/module/AI_Cdvst
Author: Philipp Juen
Author-email: support@now4free.de
License: MIT
Project-URL: Source, https://github.com/philippjuen/AI_Cdvst
Keywords: AI,creating,fine tuning,api calls,response,using
Classifier: Development Status :: 3 - Alpha
Classifier: Intended Audience :: Developers
Classifier: License :: OSI Approved :: MIT License
Classifier: Programming Language :: Python :: 3
Classifier: Programming Language :: Python :: 3.6
Classifier: Programming Language :: Python :: 3.7
Classifier: Programming Language :: Python :: 3.8
Classifier: Programming Language :: Python :: 3.9
Requires-Dist: openai
